ocx_databinding/__init__.py
ocx_databinding/cli.py
ocx_databinding/generator.py
ocx_databinding-2.8.1.dist-info/LICENSE
ocx_databinding-2.8.1.dist-info/METADATA
ocx_databinding-2.8.1.dist-info/WHEEL
ocx_databinding-2.8.1.dist-info/entry_points.txt
ocx_databinding-2.8.1.dist-info/RECORD
