Metadata-Version: 2.3
Name: ocx_databinding
Version: 2.8.1
Summary: Python CLI for managing OCX schema databinding and versioning according to PEP 440.
Home-page: https://github.com/OCXStandard/ocx-databinding
Author: ocastrup
Author-email: ole.christian.astrup@dnv.com>
Requires-Python: >=3.9,<4.0
Classifier: Programming Language :: Python :: 3
Classifier: Programming Language :: Python :: 3.9
Classifier: Programming Language :: Python :: 3.10
Classifier: Programming Language :: Python :: 3.11
Classifier: Programming Language :: Python :: 3.12
Classifier: Programming Language :: Python :: 3.13
Requires-Dist: loguru
Requires-Dist: typer
Project-URL: Bug Tracker, https://github.com/OCXStandard/ocx-databinding/issues
